dobotWrapperPy/__init__.py
dobotWrapperPy/dobotConnection.py
dobotWrapperPy/dobotControlGUI.py
dobotWrapperPy/dobotSupliment.py
dobotWrapperPy/dobotapi.py
dobotWrapperPy/dobotasync.py
dobotWrapperPy/message.py
dobotWrapperPy/paramsStructures.py
dobotWrapperPy/enums/CPMode.py
dobotWrapperPy/enums/CommunicationProtocolIDs.py
dobotWrapperPy/enums/ControlValues.py
dobotWrapperPy/enums/EMotorIndex.py
dobotWrapperPy/enums/HHTTrigMode.py
dobotWrapperPy/enums/IOFunction.py
dobotWrapperPy/enums/__init__.py
dobotWrapperPy/enums/alarm.py
dobotWrapperPy/enums/jogCmd.py
dobotWrapperPy/enums/jogMode.py
dobotWrapperPy/enums/level.py
dobotWrapperPy/enums/ptpMode.py
dobotWrapperPy/enums/realTimeTrack.py
dobotWrapperPy/enums/tagVersionColorSensorAndIR.py
dobotWrapperPy/enums/tagVersionRail.py
dobotWrapperPy/enums/triggerCondition.py
dobotWrapperPy/enums/triggerMode.py
dobotwrapperpy-1.3.0.dist-info/licenses/LICENSE
dobotwrapperpy-1.3.0.dist-info/METADATA
dobotwrapperpy-1.3.0.dist-info/WHEEL
dobotwrapperpy-1.3.0.dist-info/top_level.txt
dobotwrapperpy-1.3.0.dist-info/RECORD
