Metadata-Version: 2.4
Name: dobotWrapperPy
Version: 1.3.0
Summary: Python library for Dobot Magician For Minitechnicus Courses
Home-page: https://github.com/andreishark/dobotWrapperPy
Download-URL: https://github.com/andreishark/dobotWrapperPy
Author: Minitechnicus
Author-email: dev@minitechnicus.org
Keywords: dobot,magician,robotics,minitechnicus
License-File: LICENSE
Requires-Dist: pyserial==3.4
Dynamic: author
Dynamic: author-email
Dynamic: description
Dynamic: description-content-type
Dynamic: download-url
Dynamic: home-page
Dynamic: keywords
Dynamic: license-file
Dynamic: requires-dist
Dynamic: summary
